demo/__init__.py
demo/main.py
aapp2face-1.0.0.dist-info/METADATA
aapp2face-1.0.0.dist-info/WHEEL
aapp2face-1.0.0.dist-info/entry_points.txt
aapp2face-1.0.0.dist-info/RECORD
