Metadata-Version: 2.1
Name: aapp2face
Version: 1.0.0
Summary: Una librería Python para interactuar con los servicios web de FACe desde el lado de las Administraciones Públicas.
Requires-Python: >=3.10,<4.0
Classifier: Programming Language :: Python :: 3
Classifier: Programming Language :: Python :: 3.10
Classifier: Programming Language :: Python :: 3.11
Requires-Dist: typer[all] (>=0.7.0,<0.8.0)
Requires-Dist: zeep (>=4.2.1,<5.0.0)
